{ "columns":6,
 "image":"..\/..\/..\/..\/..\/Downloads\/classic_hero (1).png",
 "imageheight":95,
 "imagewidth":108,
 "margin":0,
 "name":"classic_hero",
 "spacing":0,
 "tilecount":30,
 "tiledversion":"1.3.1",
 "tileheight":19,
 "tiles":[
        {
         "animation":[
                {
                 "duration":150,
                 "tileid":0
                }, 
                {
                 "duration":150,
                 "tileid":1
                }, 
                {
                 "duration":150,
                 "tileid":2
                }],
         "id":2
        }, 
        {
         "animation":[
                {
                 "duration":150,
                 "tileid":6
                }, 
                {
                 "duration":150,
                 "tileid":7
                }, 
                {
                 "duration":150,
                 "tileid":8
                }, 
                {
                 "duration":150,
                 "tileid":9
                }, 
                {
                 "duration":150,
                 "tileid":10
                }, 
                {
                 "duration":150,
                 "tileid":11
                }],
         "id":6
        }, 
        {
         "animation":[
                {
                 "duration":150,
                 "tileid":18
                }, 
                {
                 "duration":150,
                 "tileid":19
                }, 
                {
                 "duration":150,
                 "tileid":20
                }, 
                {
                 "duration":150,
                 "tileid":21
                }, 
                {
                 "duration":150,
                 "tileid":22
                }, 
                {
                 "duration":150,
                 "tileid":23
                }],
         "id":23
        }, 
        {
         "animation":[
                {
                 "duration":150,
                 "tileid":24
                }, 
                {
                 "duration":150,
                 "tileid":25
                }, 
                {
                 "duration":150,
                 "tileid":26
                }],
         "id":26
        }],
 "tilewidth":18,
 "type":"tileset",
 "version":1.2
}